[
  {
    "event_id": "01cc26e6f8d5b2a9214a6dfe9d519e05",
    "event_time": "2025-02-09T02:10:36Z",
    "bookmaker": "DraftKings",
    "player_name": "Julian Strawther",
    "market": "player_threes",
    "line": 4.5,
    "price": -850,
    "home_team": "Phoenix Suns",
    "away_team": "Denver Nuggets",
    "prediction": 0.14223169897908503,
    "edge": 89.46832162157239,
    "probability": 5.362588953927716e-05,
    "confidence": 0.9841964778912128,
    "kelly": 0.9999400651822796,
    "score": 88.04912949795539
  },
  {
    "event_id": "f05d99b8a83b68dc5a0ae66a036fa3b4",
    "event_time": "2025-02-09T03:41:51Z",
    "bookmaker": "FanDuel",
    "player_name": "Keyonte George",
    "market": "player_threes",
    "line": 1.5,
    "price": -168,
    "home_team": "Los Angeles Clippers",
    "away_team": "Utah Jazz",
    "prediction": 0.14223169897908503,
    "edge": 62.355724855303805,
    "probability": 0.0033084230887530097,
    "confidence": 0.9525894336736382,
    "kelly": 0.9947222774536559,
    "score": 59.08591104918783
  },
  {
    "event_id": "f05d99b8a83b68dc5a0ae66a036fa3b4",
    "event_time": "2025-02-09T03:41:51Z",
    "bookmaker": "ESPN BET",
    "player_name": "Keyonte George",
    "market": "player_threes",
    "line": 1.5,
    "price": -165,
    "home_team": "Los Angeles Clippers",
    "away_team": "Utah Jazz",
    "prediction": 0.14223169897908503,
    "edge": 61.93330863452092,
    "probability": 0.0033084230887530097,
    "confidence": 0.9525894336736382,
    "kelly": 0.9946864720089724,
    "score": 58.68353310499021
  },
  {
    "event_id": "f05d99b8a83b68dc5a0ae66a036fa3b4",
    "event_time": "2025-02-09T03:41:51Z",
    "bookmaker": "ESPN BET",
    "player_name": "Keyonte George",
    "market": "player_assists",
    "line": 4.5,
    "price": -150,
    "home_team": "Los Angeles Clippers",
    "away_team": "Utah Jazz",
    "prediction": 0.373057988153111,
    "edge": 59.987796005030845,
    "probability": 0.00012203994969151033,
    "confidence": 0.9585491124274321,
    "kelly": 0.9997966000838474,
    "score": 57.48955286795279
  },
  {
    "event_id": "01cc26e6f8d5b2a9214a6dfe9d519e05",
    "event_time": "2025-02-09T02:10:36Z",
    "bookmaker": "Pinnacle",
    "player_name": "Julian Strawther",
    "market": "player_threes",
    "line": 2.5,
    "price": -140,
    "home_team": "Phoenix Suns",
    "away_team": "Denver Nuggets",
    "prediction": 0.14223169897908503,
    "edge": 58.32525004354251,
    "probability": 8.083289790827841e-05,
    "confidence": 0.971553660204183,
    "kelly": 0.9998614293178715,
    "score": 56.65825790058917
  },
  {
    "event_id": "f05d99b8a83b68dc5a0ae66a036fa3b4",
    "event_time": "2025-02-09T03:41:51Z",
    "bookmaker": "DraftKings",
    "player_name": "Keyonte George",
    "market": "player_threes",
    "line": 1.5,
    "price": -148,
    "home_team": "Los Angeles Clippers",
    "away_team": "Utah Jazz",
    "prediction": 0.14223169897908503,
    "edge": 59.346577045963414,
    "probability": 0.0033084230887530097,
    "confidence": 0.9525894336736382,
    "kelly": 0.9944561559053329,
    "score": 56.2195125116869
  },
  {
    "event_id": "06420b6c46a70fe5fcfb0a4ae98013eb",
    "event_time": "2025-02-09T19:00:00Z",
    "bookmaker": "Underdog",
    "player_name": "Amen Thompson",
    "market": "player_assists",
    "line": 5.5,
    "price": -137,
    "home_team": "Houston Rockets",
    "away_team": "Toronto Raptors",
    "prediction": 0.3567908328590463,
    "edge": 57.79672502140883,
    "probability": 9.182151586950571e-05,
    "confidence": 0.9675644697400867,
    "kelly": 0.9998411554798461,
    "score": 55.91317468564785
  },
  {
    "event_id": "06420b6c46a70fe5fcfb0a4ae98013eb",
    "event_time": "2025-02-09T19:00:00Z",
    "bookmaker": "Underdog",
    "player_name": "Amen Thompson",
    "market": "player_assists",
    "line": 5.5,
    "price": -137,
    "home_team": "Houston Rockets",
    "away_team": "Toronto Raptors",
    "prediction": 0.3567908328590463,
    "edge": 57.79672502140883,
    "probability": 9.182151586950571e-05,
    "confidence": 0.9675644697400867,
    "kelly": 0.9998411554798461,
    "score": 55.91317468564785
  },
  {
    "event_id": "f05d99b8a83b68dc5a0ae66a036fa3b4",
    "event_time": "2025-02-09T03:41:51Z",
    "bookmaker": "FanDuel",
    "player_name": "Keyonte George",
    "market": "player_rebounds",
    "line": 3.5,
    "price": -158,
    "home_team": "Los Angeles Clippers",
    "away_team": "Utah Jazz",
    "prediction": 0.7479413279185939,
    "edge": 61.15732622779368,
    "probability": 0.0008298384972569295,
    "confidence": 0.8931512388687723,
    "kelly": 0.9986449472639729,
    "score": 54.548724990684335
  },
  {
    "event_id": "06420b6c46a70fe5fcfb0a4ae98013eb",
    "event_time": "2025-02-09T19:00:00Z",
    "bookmaker": "Underdog",
    "player_name": "Amen Thompson",
    "market": "player_rebounds",
    "line": 8.5,
    "price": -137,
    "home_team": "Houston Rockets",
    "away_team": "Toronto Raptors",
    "prediction": 1.053374972668444,
    "edge": 57.783016203267834,
    "probability": 0.00022890969727951127,
    "confidence": 0.9380367663136209,
    "kelly": 0.9996040029324434,
    "score": 54.18112959901477
  },
  {
    "event_id": "06420b6c46a70fe5fcfb0a4ae98013eb",
    "event_time": "2025-02-09T19:00:00Z",
    "bookmaker": "Underdog",
    "player_name": "Amen Thompson",
    "market": "player_rebounds",
    "line": 8.5,
    "price": -137,
    "home_team": "Houston Rockets",
    "away_team": "Toronto Raptors",
    "prediction": 1.053374972668444,
    "edge": 57.783016203267834,
    "probability": 0.00022890969727951127,
    "confidence": 0.9380367663136209,
    "kelly": 0.9996040029324434,
    "score": 54.18112959901477
  },
  {
    "event_id": "345c1fb258b16c2a64bc7c584d928a19",
    "event_time": "2025-02-09T03:10:00Z",
    "bookmaker": "Pinnacle",
    "player_name": "Jordan Hawkins",
    "market": "player_threes",
    "line": 1.5,
    "price": -131,
    "home_team": "Sacramento Kings",
    "away_team": "New Orleans Pelicans",
    "prediction": 0.14223169897908503,
    "edge": 56.37911440108141,
    "probability": 0.0033084230887530097,
    "confidence": 0.9525894336736382,
    "kelly": 0.9941660631030387,
    "score": 53.39283037609578
  },
  {
    "event_id": "f05d99b8a83b68dc5a0ae66a036fa3b4",
    "event_time": "2025-02-09T03:41:51Z",
    "bookmaker": "DraftKings",
    "player_name": "Keyonte George",
    "market": "player_assists",
    "line": 4.5,
    "price": -125,
    "home_team": "Los Angeles Clippers",
    "away_team": "Utah Jazz",
    "prediction": 0.373057988153111,
    "edge": 55.54335156058641,
    "probability": 0.00012203994969151033,
    "confidence": 0.9585491124274321,
    "kelly": 0.9997803280905554,
    "score": 53.22933478084942
  },
  {
    "event_id": "06420b6c46a70fe5fcfb0a4ae98013eb",
    "event_time": "2025-02-09T19:00:00Z",
    "bookmaker": "Underdog",
    "player_name": "Gradey Dick",
    "market": "player_points",
    "line": 14.5,
    "price": -137,
    "home_team": "Houston Rockets",
    "away_team": "Toronto Raptors",
    "prediction": 2.312846868203333,
    "edge": 57.76721336683352,
    "probability": 0.00038693806162259925,
    "confidence": 0.9202466597171264,
    "kelly": 0.999330625397047,
    "score": 53.12450113111021
  },
  {
    "event_id": "06420b6c46a70fe5fcfb0a4ae98013eb",
    "event_time": "2025-02-09T19:00:00Z",
    "bookmaker": "Underdog",
    "player_name": "Gradey Dick",
    "market": "player_points",
    "line": 14.5,
    "price": -137,
    "home_team": "Houston Rockets",
    "away_team": "Toronto Raptors",
    "prediction": 2.312846868203333,
    "edge": 57.76721336683352,
    "probability": 0.00038693806162259925,
    "confidence": 0.9202466597171264,
    "kelly": 0.999330625397047,
    "score": 53.12450113111021
  },
  {
    "event_id": "06420b6c46a70fe5fcfb0a4ae98013eb",
    "event_time": "2025-02-09T19:00:00Z",
    "bookmaker": "Fliff",
    "player_name": "Amen Thompson",
    "market": "player_points",
    "line": 18.5,
    "price": -130,
    "home_team": "Houston Rockets",
    "away_team": "Toronto Raptors",
    "prediction": 2.308456053585181,
    "edge": 56.498552410360745,
    "probability": 0.00023186720074030998,
    "confidence": 0.9376092958490492,
    "kelly": 0.9995897734140746,
    "score": 52.95183677604782
  },
  {
    "event_id": "f05d99b8a83b68dc5a0ae66a036fa3b4",
    "event_time": "2025-02-09T03:41:51Z",
    "bookmaker": "ESPN BET",
    "player_name": "Keyonte George",
    "market": "player_points",
    "line": 15.5,
    "price": -135,
    "home_team": "Los Angeles Clippers",
    "away_team": "Utah Jazz",
    "prediction": 2.3962549487466154,
    "edge": 57.410777536701396,
    "probability": 0.00036030973936906907,
    "confidence": 0.9227014532662382,
    "kelly": 0.9993727941573944,
    "score": 52.939782886224975
  },
  {
    "event_id": "06420b6c46a70fe5fcfb0a4ae98013eb",
    "event_time": "2025-02-09T19:00:00Z",
    "bookmaker": "Fliff",
    "player_name": "Amen Thompson",
    "market": "player_assists",
    "line": 5.5,
    "price": -120,
    "home_team": "Houston Rockets",
    "away_team": "Toronto Raptors",
    "prediction": 0.3567908328590463,
    "edge": 54.53627239386759,
    "probability": 9.182151586950571e-05,
    "confidence": 0.9675644697400867,
    "kelly": 0.9998316605542392,
    "score": 52.758476652324234
  },
  {
    "event_id": "06420b6c46a70fe5fcfb0a4ae98013eb",
    "event_time": "2025-02-09T19:00:00Z",
    "bookmaker": "Fliff",
    "player_name": "Amen Thompson",
    "market": "player_assists",
    "line": 5.5,
    "price": -120,
    "home_team": "Houston Rockets",
    "away_team": "Toronto Raptors",
    "prediction": 0.3567908328590463,
    "edge": 54.53627239386759,
    "probability": 9.182151586950571e-05,
    "confidence": 0.9675644697400867,
    "kelly": 0.9998316605542392,
    "score": 52.758476652324234
  },
  {
    "event_id": "f05d99b8a83b68dc5a0ae66a036fa3b4",
    "event_time": "2025-02-09T03:41:51Z",
    "bookmaker": "FanDuel",
    "player_name": "Keyonte George",
    "market": "player_assists",
    "line": 4.5,
    "price": -120,
    "home_team": "Los Angeles Clippers",
    "away_team": "Utah Jazz",
    "prediction": 0.373057988153111,
    "edge": 54.53325055048539,
    "probability": 0.00012203994969151033,
    "confidence": 0.9585491124274321,
    "kelly": 0.9997762600922321,
    "score": 52.26110340174299
  },
  {
    "event_id": "f05d99b8a83b68dc5a0ae66a036fa3b4",
    "event_time": "2025-02-09T03:41:51Z",
    "bookmaker": "FanDuel",
    "player_name": "Keyonte George",
    "market": "player_points",
    "line": 15.5,
    "price": -130,
    "home_team": "Los Angeles Clippers",
    "away_team": "Utah Jazz",
    "prediction": 2.3962549487466154,
    "edge": 56.48570815649787,
    "probability": 0.00036030973936906907,
    "confidence": 0.9227014532662382,
    "kelly": 0.9993625289226545,
    "score": 52.08622036601535
  },
  {
    "event_id": "f05d99b8a83b68dc5a0ae66a036fa3b4",
    "event_time": "2025-02-09T03:41:51Z",
    "bookmaker": "DraftKings",
    "player_name": "Keyonte George",
    "market": "player_rebounds",
    "line": 4.5,
    "price": -130,
    "home_team": "Los Angeles Clippers",
    "away_team": "Utah Jazz",
    "prediction": 0.7479413279185939,
    "edge": 56.47911446432226,
    "probability": 0.00042624666112522913,
    "confidence": 0.9168954080090451,
    "kelly": 0.9992458712918555,
    "score": 51.74638781325797
  },
  {
    "event_id": "033ffd442857285ce6fc168666e1283d",
    "event_time": "2025-02-09T18:00:00Z",
    "bookmaker": "Fliff",
    "player_name": "Ausar Thompson",
    "market": "player_points",
    "line": 10.5,
    "price": -135,
    "home_team": "Detroit Pistons",
    "away_team": "Charlotte Hornets",
    "prediction": 2.212300589644028,
    "edge": 57.36716762666691,
    "probability": 0.0007964088397138802,
    "confidence": 0.894652352874094,
    "kelly": 0.9986136586864239,
    "score": 51.25251936876229
  },
  {
    "event_id": "06420b6c46a70fe5fcfb0a4ae98013eb",
    "event_time": "2025-02-09T19:00:00Z",
    "bookmaker": "Fliff",
    "player_name": "Amen Thompson",
    "market": "player_rebounds",
    "line": 8.5,
    "price": -120,
    "home_team": "Houston Rockets",
    "away_team": "Toronto Raptors",
    "prediction": 1.053374972668444,
    "edge": 54.52256357572659,
    "probability": 0.00022890969727951127,
    "confidence": 0.9380367663136209,
    "kelly": 0.9995803322216544,
    "score": 51.122705667828264
  },
  {
    "event_id": "06420b6c46a70fe5fcfb0a4ae98013eb",
    "event_time": "2025-02-09T19:00:00Z",
    "bookmaker": "Fliff",
    "player_name": "Amen Thompson",
    "market": "player_rebounds",
    "line": 8.5,
    "price": -120,
    "home_team": "Houston Rockets",
    "away_team": "Toronto Raptors",
    "prediction": 1.053374972668444,
    "edge": 54.52256357572659,
    "probability": 0.00022890969727951127,
    "confidence": 0.9380367663136209,
    "kelly": 0.9995803322216544,
    "score": 51.122705667828264
  },
  {
    "event_id": "01cc26e6f8d5b2a9214a6dfe9d519e05",
    "event_time": "2025-02-09T02:10:36Z",
    "bookmaker": "Pinnacle",
    "player_name": "Julian Strawther",
    "market": "player_points",
    "line": 13.5,
    "price": -129,
    "home_team": "Phoenix Suns",
    "away_team": "Denver Nuggets",
    "prediction": 2.8099594408078685,
    "edge": 56.254978567548086,
    "probability": 0.000768991617095538,
    "confidence": 0.895927428118227,
    "kelly": 0.9986348908502722,
    "score": 50.33157624934749
  },
  {
    "event_id": "f05d99b8a83b68dc5a0ae66a036fa3b4",
    "event_time": "2025-02-09T03:41:51Z",
    "bookmaker": "DraftKings",
    "player_name": "Keyonte George",
    "market": "player_points",
    "line": 15.5,
    "price": -120,
    "home_team": "Los Angeles Clippers",
    "away_team": "Utah Jazz",
    "prediction": 2.3962549487466154,
    "edge": 54.50942357151764,
    "probability": 0.00036030973936906907,
    "confidence": 0.9227014532662382,
    "kelly": 0.9993394321444898,
    "score": 50.26270047525803
  },
  {
    "event_id": "f05d99b8a83b68dc5a0ae66a036fa3b4",
    "event_time": "2025-02-09T03:41:51Z",
    "bookmaker": "FanDuel",
    "player_name": "Keyonte George",
    "market": "player_assists",
    "line": 4.5,
    "price": -110,
    "home_team": "Los Angeles Clippers",
    "away_team": "Utah Jazz",
    "prediction": 0.373057988153111,
    "edge": 52.36874838598323,
    "probability": 0.00012203994969151033,
    "confidence": 0.9585491124274321,
    "kelly": 0.999767014641498,
    "score": 50.18632188126667
  },
  {
    "event_id": "06420b6c46a70fe5fcfb0a4ae98013eb",
    "event_time": "2025-02-09T19:00:00Z",
    "bookmaker": "Fliff",
    "player_name": "Gradey Dick",
    "market": "player_points",
    "line": 14.5,
    "price": -120,
    "home_team": "Houston Rockets",
    "away_team": "Toronto Raptors",
    "prediction": 2.312846868203333,
    "edge": 54.50676073929228,
    "probability": 0.00038693806162259925,
    "confidence": 0.9202466597171264,
    "kelly": 0.9992906135536919,
    "score": 50.12408191618501
  },
  {
    "event_id": "06420b6c46a70fe5fcfb0a4ae98013eb",
    "event_time": "2025-02-09T19:00:00Z",
    "bookmaker": "Fliff",
    "player_name": "Gradey Dick",
    "market": "player_points",
    "line": 14.5,
    "price": -120,
    "home_team": "Houston Rockets",
    "away_team": "Toronto Raptors",
    "prediction": 2.312846868203333,
    "edge": 54.50676073929228,
    "probability": 0.00038693806162259925,
    "confidence": 0.9202466597171264,
    "kelly": 0.9992906135536919,
    "score": 50.12408191618501
  },
  {
    "event_id": "f05d99b8a83b68dc5a0ae66a036fa3b4",
    "event_time": "2025-02-09T03:41:51Z",
    "bookmaker": "DraftKings",
    "player_name": "Keyonte George",
    "market": "player_assists",
    "line": 4.5,
    "price": -105,
    "home_team": "Los Angeles Clippers",
    "away_team": "Utah Jazz",
    "prediction": 0.373057988153111,
    "edge": 51.2073082001528,
    "probability": 0.00012203994969151033,
    "confidence": 0.9585491124274321,
    "kelly": 0.9997617315267927,
    "score": 49.07302448380391
  },
  {
    "event_id": "06420b6c46a70fe5fcfb0a4ae98013eb",
    "event_time": "2025-02-09T19:00:00Z",
    "bookmaker": "Fliff",
    "player_name": "Amen Thompson",
    "market": "player_points",
    "line": 18.5,
    "price": -110,
    "home_team": "Houston Rockets",
    "away_team": "Toronto Raptors",
    "prediction": 2.308456053585181,
    "edge": 52.35776566087835,
    "probability": 0.00023186720074030998,
    "confidence": 0.9376092958490492,
    "kelly": 0.9995573444349504,
    "score": 49.06939733261331
  },
  {
    "event_id": "345c1fb258b16c2a64bc7c584d928a19",
    "event_time": "2025-02-09T03:10:00Z",
    "bookmaker": "Pinnacle",
    "player_name": "Jordan Hawkins",
    "market": "player_points",
    "line": 7.5,
    "price": -142,
    "home_team": "Sacramento Kings",
    "away_team": "New Orleans Pelicans",
    "prediction": 2.485110061996632,
    "edge": 58.30360254365989,
    "probability": 0.0037408340675333385,
    "confidence": 0.8343259958668912,
    "kelly": 0.9936247757440627,
    "score": 48.33409349936348
  },
  {
    "event_id": "f05d99b8a83b68dc5a0ae66a036fa3b4",
    "event_time": "2025-02-09T03:41:51Z",
    "bookmaker": "DraftKings",
    "player_name": "Keyonte George",
    "market": "player_points",
    "line": 15.5,
    "price": -110,
    "home_team": "Los Angeles Clippers",
    "away_team": "Utah Jazz",
    "prediction": 2.3962549487466154,
    "edge": 52.34492140701548,
    "probability": 0.00036030973936906907,
    "confidence": 0.9227014532662382,
    "kelly": 0.9993121359521134,
    "score": 48.2655120899586
  },
  {
    "event_id": "345c1fb258b16c2a64bc7c584d928a19",
    "event_time": "2025-02-09T03:10:00Z",
    "bookmaker": "Pinnacle",
    "player_name": "Jordan Hawkins",
    "market": "player_threes",
    "line": 1.5,
    "price": -101,
    "home_team": "Sacramento Kings",
    "away_team": "New Orleans Pelicans",
    "prediction": 0.14223169897908503,
    "edge": 49.91791391003018,
    "probability": 0.0033084230887530097,
    "confidence": 0.9525894336736382,
    "kelly": 0.9934159104867393,
    "score": 47.23819547523727
  },
  {
    "event_id": "f05d99b8a83b68dc5a0ae66a036fa3b4",
    "event_time": "2025-02-09T03:41:51Z",
    "bookmaker": "ESPN BET",
    "player_name": "Keyonte George",
    "market": "player_points",
    "line": 15.5,
    "price": -105,
    "home_team": "Los Angeles Clippers",
    "away_team": "Utah Jazz",
    "prediction": 2.3962549487466154,
    "edge": 51.18348122118505,
    "probability": 0.00036030973936906907,
    "confidence": 0.9227014532662382,
    "kelly": 0.9992965381278983,
    "score": 47.19385006117369
  },
  {
    "event_id": "f05d99b8a83b68dc5a0ae66a036fa3b4",
    "event_time": "2025-02-09T03:41:51Z",
    "bookmaker": "FanDuel",
    "player_name": "Keyonte George",
    "market": "player_points",
    "line": 15.5,
    "price": -102,
    "home_team": "Los Angeles Clippers",
    "away_team": "Utah Jazz",
    "prediction": 2.3962549487466154,
    "edge": 50.45901853101359,
    "probability": 0.00036030973936906907,
    "confidence": 0.9227014532662382,
    "kelly": 0.9992864454181123,
    "score": 46.52538761965587
  },
  {
    "event_id": "033ffd442857285ce6fc168666e1283d",
    "event_time": "2025-02-09T18:00:00Z",
    "bookmaker": "Fliff",
    "player_name": "Ausar Thompson",
    "market": "player_points",
    "line": 10.5,
    "price": -105,
    "home_team": "Detroit Pistons",
    "away_team": "Charlotte Hornets",
    "prediction": 2.212300589644028,
    "edge": 51.139871311150564,
    "probability": 0.0007964088397138802,
    "confidence": 0.894652352874094,
    "kelly": 0.9984451065510349,
    "score": 45.68126607753348
  },
  {
    "event_id": "01cc26e6f8d5b2a9214a6dfe9d519e05",
    "event_time": "2025-02-09T02:10:36Z",
    "bookmaker": "Pinnacle",
    "player_name": "Julian Strawther",
    "market": "player_points",
    "line": 13.5,
    "price": -103,
    "home_team": "Phoenix Suns",
    "away_team": "Denver Nuggets",
    "prediction": 2.8099594408078685,
    "edge": 50.66201709444809,
    "probability": 0.000768991617095538,
    "confidence": 0.895927428118227,
    "kelly": 0.9984844145798989,
    "score": 45.32069902841206
  },
  {
    "event_id": "345c1fb258b16c2a64bc7c584d928a19",
    "event_time": "2025-02-09T03:10:00Z",
    "bookmaker": "DraftKings",
    "player_name": "Jordan Hawkins",
    "market": "player_threes",
    "line": 0.5,
    "price": -168,
    "home_team": "Sacramento Kings",
    "away_team": "New Orleans Pelicans",
    "prediction": 0.14223169897908503,
    "edge": 38.97269055055577,
    "probability": 0.23713876613623341,
    "confidence": 0.5366524515313724,
    "kelly": 0.621707206401723,
    "score": 13.002875617825772
  }
]